grapht/__init__.py
grapht/_nbdev.py
grapht/graphtools.py
grapht/sampling.py
grapht/spectral.py
grapht-0.0.1.dist-info/LICENSE
grapht-0.0.1.dist-info/METADATA
grapht-0.0.1.dist-info/WHEEL
grapht-0.0.1.dist-info/entry_points.txt
grapht-0.0.1.dist-info/top_level.txt
grapht-0.0.1.dist-info/RECORD
